CHANGELOG.rst
README.rst
snug/__init__.py
snug/clients.py
snug/http.py
snug/pagination.py
snug/query.py
snug-2.4.0.dist-info/LICENSE
snug-2.4.0.dist-info/WHEEL
snug-2.4.0.dist-info/METADATA
snug-2.4.0.dist-info/RECORD
