Metadata-Version: 2.1
Name: snug
Version: 2.4.0
Summary: Write reusable web API interactions
Home-page: https://github.com/ariebovenberg/snug
License: MIT
Keywords: api-wrapper,http,async,graphql,rest
Author: Arie Bovenberg
Author-email: a.c.bovenberg@gmail.com
Requires-Python: >=3.7,<4.0
Classifier: Development Status :: 4 - Beta
Classifier: License :: OSI Approved :: MIT License
Classifier: Programming Language :: Python :: 3
Classifier: Programming Language :: Python :: 3.7
Classifier: Programming Language :: Python :: 3.8
Classifier: Programming Language :: Python :: 3.9
Classifier: Programming Language :: Python :: 3.10
Classifier: Programming Language :: Python :: 3.11
Classifier: Programming Language :: Python :: 3.10
Classifier: Programming Language :: Python :: 3.11
Classifier: Programming Language :: Python :: 3.7
Classifier: Programming Language :: Python :: 3.8
Classifier: Programming Language :: Python :: 3.9
Classifier: Topic :: Software Development :: Libraries :: Python Modules
Provides-Extra: aiohttp
Provides-Extra: httpx
Provides-Extra: requests
Requires-Dist: aiohttp (>=3.4.4,<4.0.0); extra == "aiohttp"
Requires-Dist: httpx (>=0.21.1,<0.23.0); extra == "httpx"
Requires-Dist: importlib-metadata (>=1,<5); python_version < "3.8"
Requires-Dist: requests (>=2.20,<3.0); extra == "requests"
Project-URL: Repository, https://github.com/ariebovenberg/snug
